jacoco_reporter/__init__.py
jacoco_reporter/jacoco_reporter.py
jacoco_reporter/mcp-jacoco-reporter-server.py
jacoco_reporter/server.py
jacoco_reporter/test_jacoco.xml
jacoco_reporter-0.1.0.dist-info/WHEEL
jacoco_reporter-0.1.0.dist-info/entry_points.txt
jacoco_reporter-0.1.0.dist-info/METADATA
jacoco_reporter-0.1.0.dist-info/RECORD
