Metadata-Version: 2.3
Name: jacoco-reporter
Version: 0.1.0
Summary: A MCP server project
Author: 渝江
Author-email: 渝江 <chennanlin.cnl@alibaba-inc.com>
Requires-Dist: mcp>=1.6.0
Requires-Python: >=3.13
